[
  { "route": "", "active": "1", "descendant": "", "entity": "8ly2h5zc", "template": "", "type": "web_article", "relative": "1" },
  { "route": "Tiền_đồng_lớn/Minh_Mệnh_thông_bảo/Hiền_hiền_thân_thân_lạc_lạc_lợi_lợi/BJCX_2005_1368", "active": "1", "descendant": "", "entity": "84wauvgm", "template": "", "type": "web_article", "relative": "0" },
  { "route": "Tiền_đồng_lớn/Minh_Mệnh_thông_bảo/Hiền_hiền_thân_thân_lạc_lạc_lợi_lợi/Barker_140", "active": "1", "descendant": "", "entity": "n4r9rszp", "template": "", "type": "web_article", "relative": "0" },
  { "route": "Tiền_đồng_lớn/Minh_Mệnh_thông_bảo/Quốc_thái_dân_an_phong_điều_vũ_thuận/CHCOIN_37711", "active": "1", "descendant": "", "entity": "p7qjqpxq", "template": "", "type": "web_article", "relative": "0" },
  { "route": "Tiền_đồng_lớn/Minh_Mệnh_thông_bảo/Hoa_phong_tam_chúc_thiên_bảo_cửu_như/BJCX_2005_1369", "active": "1", "descendant": "", "entity": "2ibsgbkt", "template": "", "type": "web_article", "relative": "0" },
  { "route": "Tiền_đồng_lớn/Minh_Mệnh_thông_bảo/Đắc_vị_đắc_lộc_đắc_danh_đắc_thọ/SHCY_2011_1287", "active": "1", "descendant": "", "entity": "8pbvxf1n", "template": "", "type": "web_article", "relative": "0" },
  { "route": "Tiền_đồng_lớn/Minh_Mệnh_thông_bảo/Lục_phủ_khổng_tu_tam_sự_doãn_trị/Barker_144", "active": "1", "descendant": "", "entity": "kuptqi54", "template": "", "type": "web_article", "relative": "0" },
  { "route": "Tiền_đồng_lớn/Minh_Mệnh_thông_bảo/Chí_công_chí_chính_vô_đảng_vô_thiên/Barker_145", "active": "1", "descendant": "", "entity": "hyw0c4np", "template": "", "type": "web_article", "relative": "0" },
  { "route": "Tiền_đồng_lớn/Minh_Mệnh_thông_bảo/Vạn_tuế_vạn_tuế_vạn_vạn_tuế_thọ/CHCOIN_27107", "active": "1", "descendant": "", "entity": "7pnp0b5a", "template": "", "type": "web_article", "relative": "0" },
  { "route": "Tiền_đồng_lớn/Minh_Mệnh_thông_bảo/Mục_mục_hoàng_hoàng_tể_tể_thương_thương/Barker_147", "active": "1", "descendant": "", "entity": "d3wdkmez", "template": "", "type": "web_article", "relative": "0" },
  { "route": "Tiền_đồng_lớn/Minh_Mệnh_thông_bảo/Hà_lưu_thuận_quỉ_niên_cốc_phong_đăng/Barker_148", "active": "1", "descendant": "", "entity": "0tg1b52u", "template": "", "type": "web_article", "relative": "0" },
  { "route": "Tiền_đồng_lớn/Minh_Mệnh_thông_bảo/Thân_thân_trưởng_trưởng_lão_lão_ấu_ấu/Barker_149", "active": "1", "descendant": "", "entity": "7oh7uk48", "template": "", "type": "web_article", "relative": "0" },
  { "route": "Tiền_đồng_lớn/Minh_Mệnh_thông_bảo/Quốc_phú_binh_cường_nội_an_ngoại_tĩnh/HUAY_18_0528_223", "active": "1", "descendant": "", "entity": "xj4nd19m", "template": "", "type": "web_article", "relative": "0" },
  { "route": "Tiền_đồng_lớn/Minh_Mệnh_thông_bảo/Như_sơn_như_xuyên_như_cương_như_phụ/Barker_151", "active": "1", "descendant": "", "entity": "vc0j8fqz", "template": "", "type": "web_article", "relative": "0" },
  { "route": "Tiền_đồng_lớn/Minh_Mệnh_thông_bảo/Quân_quân_thần_thần_phụ_phụ_tử_tử/ZGJD_2011_2374", "active": "1", "descendant": "", "entity": "ztt8d4a9", "template": "", "type": "web_article", "relative": "0" },
  { "route": "Tiền_đồng_lớn/Minh_Mệnh_thông_bảo/Phúc_như_đông_hải_thọ_tỳ_nam_sơn/Barker_152", "active": "1", "descendant": "", "entity": "ul1vjnjq", "template": "", "type": "web_article", "relative": "0" },
  { "route": "Tiền_đồng_lớn/Minh_Mệnh_thông_bảo/Vạn_thọ_du_tạc_vạn_phúc_du_đồng/Barker_155", "active": "1", "descendant": "", "entity": "l2k5xst2", "template": "", "type": "web_article", "relative": "0" },
  { "route": "Tiền_đồng_lớn/Minh_Mệnh_thông_bảo/Thiên_bất_ái_đạo_địa_bất_ái_bảo/Barker_154", "active": "1", "descendant": "", "entity": "vejbbs3v", "template": "", "type": "web_article", "relative": "0" },
  { "route": "Tiền_đồng_lớn/Minh_Mệnh_thông_bảo/Truy_trác_kỳ_chương_kim_ngọc_kỳ_tương/Barker_156", "active": "1", "descendant": "", "entity": "kgsch3ct", "template": "", "type": "web_article", "relative": "0" },
  { "route": "Tiền_đồng_lớn/Minh_Mệnh_thông_bảo/Vương_đạo_đãng_đãng_thánh_mô_dương_dương/BJHH_2011_0683_1", "active": "1", "descendant": "", "entity": "ax3dll9y", "template": "", "type": "web_article", "relative": "0" },
  { "route": "Tiền_đồng_lớn/Minh_Mệnh_thông_bảo/Nhất_nhân_hữu_khánh_vạn_thọ_vô_cương/Barker_157", "active": "1", "descendant": "", "entity": "or2hioz4", "template": "", "type": "web_article", "relative": "0" },
  { "route": "Tiền_đồng_lớn/Minh_Mệnh_thông_bảo/Nhất_nhân_hữu_khánh_vạn_thọ_vô_cương/Guangxi_439", "active": "1", "descendant": "", "entity": "ax55vl5j", "template": "", "type": "web_article", "relative": "0" },
  { "route": "Tiền_đồng_lớn/Minh_Mệnh_thông_bảo/Ngũ_thời_thuận_phủ_thứ_tích_kỳ_ngưng/Barker_158", "active": "1", "descendant": "", "entity": "c4g081fu", "template": "", "type": "web_article", "relative": "0" },
  { "route": "Tiền_đồng_lớn/Minh_Mệnh_thông_bảo/Nguyên_hanh_lợi_trinh/Barker_159", "active": "1", "descendant": "", "entity": "afd77t5v", "template": "", "type": "web_article", "relative": "0" },
  { "route": "Tiền_đồng_lớn/Minh_Mệnh_thông_bảo/Phúc_lỷ_tuy_tướng/Barker_160", "active": "1", "descendant": "", "entity": "bbhu2u5v", "template": "", "type": "web_article", "relative": "0" },
  { "route": "Tiền_đồng_lớn/Minh_Mệnh_thông_bảo/Đế_đức_quảng_vận/BJCX_2006_2411", "active": "1", "descendant": "", "entity": "8mozbhyn", "template": "", "type": "web_article", "relative": "0" },
  { "route": "Tiền_đồng_lớn/Minh_Mệnh_thông_bảo/Đế_đức_quảng_vận/Barker_161", "active": "1", "descendant": "", "entity": "57kyetz4", "template": "", "type": "web_article", "relative": "0" },
  { "route": "Tiền_đồng_lớn/Minh_Mệnh_thông_bảo/Lợi_dụng_hậu_sinh/Guangxi_423", "active": "1", "descendant": "", "entity": "vfs85dir", "template": "", "type": "web_article", "relative": "0" },
  { "route": "Tiền_đồng_lớn/Minh_Mệnh_thông_bảo/Trung_hoà_vị_dục/BJCX_2007_1158", "active": "1", "descendant": "", "entity": "ypnhqa17", "template": "", "type": "web_article", "relative": "0" },
  { "route": "Tiền_đồng_lớn/Minh_Mệnh_thông_bảo/Liễm_phúc_tích_dân/JNQ_16", "active": "1", "descendant": "", "entity": "24bgeugv", "template": "", "type": "web_article", "relative": "0" },
  { "route": "Tiền_đồng_lớn/Minh_Mệnh_thông_bảo/Tứ_phương_vi_tắc/Barker_164", "active": "1", "descendant": "", "entity": "c5abfhym", "template": "", "type": "web_article", "relative": "0" },
  { "route": "Tiền_đồng_lớn/Minh_Mệnh_thông_bảo/Cương_kiện_trung_chính/Barker_165", "active": "1", "descendant": "", "entity": "88fhb830", "template": "", "type": "web_article", "relative": "0" },
  { "route": "Tiền_đồng_lớn/Minh_Mệnh_thông_bảo/Gia_cấp_nhân_túc/Barker_166", "active": "1", "descendant": "", "entity": "oez2c9pp", "template": "", "type": "web_article", "relative": "0" },
  { "route": "Tiền_đồng_lớn/Minh_Mệnh_thông_bảo/Xuyên_chí_sơn_tăng/BJCX_2007_1157", "active": "1", "descendant": "", "entity": "3zapctdn", "template": "", "type": "web_article", "relative": "0" },
  { "route": "Tiền_đồng_lớn/Minh_Mệnh_thông_bảo/Tự_thiên_hựu_chi_cát_vô_bất_lợi/JNQ2_1", "active": "1", "descendant": "x", "entity": "izlgufz1", "template": "", "type": "web_article", "relative": "0" },
  { "route": "Tiền_đồng_lớn/Minh_Mệnh_thông_bảo/Tứ_hải_cộng_chi_vạn_thế_truyền_chi/JNQ2_2", "active": "1", "descendant": "x", "entity": "100j47mz", "template": "", "type": "web_article", "relative": "0" },
  { "route": "Tiền_đồng_lớn/Minh_Mệnh_thông_bảo/Tứ_hải_cộng_chi_vạn_thế_truyền_chi/Schroeder_149", "active": "1", "descendant": "x", "entity": "dnj2clvp", "template": "", "type": "web_article", "relative": "0" },
  { "route": "Tiền_đồng_lớn/Minh_Mệnh_thông_bảo/Thiên_hạ_đại_đồng/JNQ2_3", "active": "1", "descendant": "x", "entity": "ugjcpmvo", "template": "", "type": "web_article", "relative": "0" },
  { "route": "Tiền_đồng_lớn/Thiệu_Trị_thông_bảo/Tự_thiên_hựu_chi_cát_vô_bất_lợi/JNQ_20", "active": "1", "descendant": "", "entity": "mlls1qr8", "template": "", "type": "web_article", "relative": "0" },
  { "route": "Tiền_đồng_lớn/Thiệu_Trị_thông_bảo/Trạch_cập_đang_thì_ân_thuỳ_vạn_thế/DJHT_2013_1381", "active": "1", "descendant": "", "entity": "frig1qnq", "template": "", "type": "web_article", "relative": "0" },
  { "route": "Tiền_đồng_lớn/Thiệu_Trị_thông_bảo/Tứ_hải_cộng_chi_vạn_thế_truyền_chi/MDP_V146", "active": "1", "descendant": "", "entity": "3mvbwa54", "template": "", "type": "web_article", "relative": "0" },
  { "route": "Tiền_đồng_lớn/Thiệu_Trị_thông_bảo/Tứ_hải_cộng_chi_vạn_thế_truyền_chi/AW_22_523", "active": "1", "descendant": "", "entity": "jaxlp339", "template": "", "type": "web_article", "relative": "0" },
  { "route": "Tiền_đồng_lớn/Thiệu_Trị_thông_bảo/Nhất_nhân_hữu_khánh_triệu_dân_lại_chi/Mitsuru_33", "active": "1", "descendant": "", "entity": "fmbf7rvh", "template": "", "type": "web_article", "relative": "0" },
  { "route": "Tiền_đồng_lớn/Thiệu_Trị_thông_bảo/Vạn_thế_vĩnh_lại/Guangxi_451", "active": "1", "descendant": "", "entity": "27bsztjk", "template": "", "type": "web_article", "relative": "0" },
  { "route": "Tiền_đồng_lớn/Thiệu_Trị_thông_bảo/Giải_ôn_phụ_tài/CHCOIN_2522059", "active": "1", "descendant": "", "entity": "r9m3fvs2", "template": "", "type": "web_article", "relative": "0" },
  { "route": "Tiền_đồng_lớn/Thiệu_Trị_thông_bảo/Thiên_hạ_đại_đồng/BJCX_2006_1265", "active": "1", "descendant": "", "entity": "lw3oadjt", "template": "", "type": "web_article", "relative": "0" },
  { "route": "Tiền_đồng_lớn/Thiệu_Trị_thông_bảo/Thọ_khảo_vạn_niên/Mitsuru_37", "active": "1", "descendant": "", "entity": "drabnjz2", "template": "", "type": "web_article", "relative": "0" },
  { "route": "Tiền_đồng_lớn/Thiệu_Trị_thông_bảo/Du_cửu_vô_cương/Mitsuru_38", "active": "1", "descendant": "", "entity": "3wogy7bp", "template": "", "type": "web_article", "relative": "0" },
  { "route": "Tiền_đồng_lớn/Thiệu_Trị_thông_bảo/Xuyên_chí_sơn_tăng/BJHH_2011_0682", "active": "1", "descendant": "", "entity": "mdcrf8zw", "template": "", "type": "web_article", "relative": "0" },
  { "route": "Tiền_đồng_lớn/Thiệu_Trị_thông_bảo/Phúc_lỷ_tuy_tướng/SHCY_2011_1368", "active": "1", "descendant": "", "entity": "zwgsb3d5", "template": "", "type": "web_article", "relative": "0" },
  { "route": "Tiền_đồng_lớn/Thiệu_Trị_thông_bảo/Nguyên_hanh_lợi_trinh/JNQ_30", "active": "1", "descendant": "", "entity": "8m3ghg5o", "template": "", "type": "web_article", "relative": "0" },
  { "route": "Tiền_đồng_lớn/Thiệu_Trị_thông_bảo/Vạn_thọ_du_tạc_vạn_phúc_du_đồng/JNQ_29", "active": "1", "descendant": "", "entity": "8gcursmz", "template": "", "type": "web_article", "relative": "0" },
  { "route": "Tiền_đồng_lớn/Tự_Đức_thông_bảo/Hiển_hiển_lệnh_đức_nghi_dân_nghi_nhân/HUAY_18_0906_141", "active": "1", "descendant": "", "entity": "rczduycc", "template": "", "type": "web_article", "relative": "0" },
  { "route": "Tiền_đồng_lớn/Tự_Đức_thông_bảo/Cao_minh_phối_thiên_bạc_hậu_phối_địa/JNQ_22", "active": "1", "descendant": "", "entity": "b0qi7xlo", "template": "", "type": "web_article", "relative": "0" },
  { "route": "Tiền_đồng_lớn/Tự_Đức_thông_bảo/Như_khuê_như_chương_lệnh_văn_lệnh_vọng/CHCOIN_906534", "active": "1", "descendant": "", "entity": "wsvammrg", "template": "", "type": "web_article", "relative": "0" },
  { "route": "Tiền_đồng_lớn/Tự_Đức_thông_bảo/Thụ_lộc_vu_thiên_bảo_hựu_mạng_chi/JNQ_25", "active": "1", "descendant": "", "entity": "k49nn14h", "template": "", "type": "web_article", "relative": "0" },
  { "route": "Tiền_đồng_lớn/Tự_Đức_thông_bảo/Cửu_công_duy_tự/MDP_V220", "active": "1", "descendant": "", "entity": "mzdhg2iv", "template": "", "type": "web_article", "relative": "0" },
  { "route": "Tiền_đồng_lớn/Tự_Đức_thông_bảo/Kinh_luân_thiên_hạ/Seigo_24", "active": "1", "descendant": "", "entity": "5qg7xcwi", "template": "", "type": "web_article", "relative": "0" },
  { "route": "Tiền_đồng_lớn/Tự_Đức_thông_bảo/Thứ_chính_duy_hòa/CN_96_4_5", "active": "1", "descendant": "", "entity": "g89x459f", "template": "", "type": "web_article", "relative": "0" },
  { "route": "Tiền_đồng_lớn/Tự_Đức_thông_bảo/Dụ_quốc_lợi_dân/JNQ2_4", "active": "1", "descendant": "x", "entity": "knqemkbg", "template": "", "type": "web_article", "relative": "0" },
  { "route": "Tiền_đồng_lớn/Tự_Đức_thông_bảo/Cương_kiện_trung_chính/JNQ2_5", "active": "1", "descendant": "x", "entity": "mehsvjsl", "template": "", "type": "web_article", "relative": "0" },
  { "route": "Tiền_đồng_lớn/Tự_Đức_thông_bảo/Vạn_thọ_du_tạc_vạn_phúc_du_đồng/JNQ_27", "active": "1", "descendant": "", "entity": "xto2injn", "template": "", "type": "web_article", "relative": "0" },
  { "route": "Tiền_đồng_lớn/Tự_Đức_thông_bảo/Chí_công_chí_chính_vô_đảng_vô_thiên/ZGJD_2007_6323", "active": "1", "descendant": "", "entity": "g8nzqp2s", "template": "", "type": "web_article", "relative": "0" },
  { "route": "Tiền_đồng_lớn/Tự_Đức_thông_bảo/Hà_lưu_thuận_quỉ_niên_cốc_phong_đăng/HOSA_S11060924", "active": "1", "descendant": "", "entity": "d9e1w2vh", "template": "", "type": "web_article", "relative": "0" },
  { "route": "Tiền_đồng_lớn/Tự_Đức_thông_bảo/Phúc_như_đông_hải_thọ_tỳ_nam_sơn/JNQ2_6", "active": "1", "descendant": "x", "entity": "qktvb14y", "template": "", "type": "web_article", "relative": "0" },
  { "route": "Tiền_đồng_lớn/Tự_Đức_thông_bảo/Tứ_hải_cộng_chi_vạn_thế_truyền_chi/JNQ_33", "active": "1", "descendant": "", "entity": "b3r3351u", "template": "", "type": "web_article", "relative": "0" },
  { "route": "Tiền_đồng_lớn/Tự_Đức_thông_bảo/Tứ_phương_vi_tắc/JNQ_34", "active": "1", "descendant": "", "entity": "2al039g8", "template": "", "type": "web_article", "relative": "0" },
  { "route": "Tiền_đồng_lớn/Tự_Đức_thông_bảo/Nguyên_hanh_lợi_trinh/CHCOIN_535988", "active": "1", "descendant": "", "entity": "drrczgik", "template": "", "type": "web_article", "relative": "0" },
  { "route": "Tiền_đồng_lớn/Tự_Đức_thông_bảo/Thân_thân_trưởng_trưởng_lão_lão_ấu_ấu/Guangxi_479", "active": "1", "descendant": "", "entity": "yghi5lit", "template": "", "type": "web_article", "relative": "0" },
  { "route": "Tiền_đồng_lớn/Tự_Đức_thông_bảo/Hà_lưu_thuận_quỉ_niên_cốc_phong_đăng/JNQ_32", "active": "1", "descendant": "", "entity": "f3kheqox", "template": "", "type": "web_article", "relative": "0" },
  { "route": "Tiền_đồng_lớn/Tự_Đức_thông_bảo/Du_cửu_vô_cương/BJCX_2006_1264", "active": "1", "descendant": "", "entity": "b8msozp5", "template": "", "type": "web_article", "relative": "0" },
  { "route": "Tiền_đồng_lớn/Tự_Đức_thông_bảo/Quốc_thái_dân_an_phong_điều_vũ_thuận/BJCX_2007_1156", "active": "1", "descendant": "", "entity": "c8rzd9cm", "template": "", "type": "web_article", "relative": "0" },
  { "route": "Tiền_đồng_lớn/Tự_Đức_thông_bảo/Thọ_khảo_vạn_niên/BSCC_2889129941", "active": "1", "descendant": "", "entity": "nhq3ujah", "template": "", "type": "web_article", "relative": "0" },
  { "route": "Tiền_đồng_lớn/Tự_Đức_thông_bảo/Hà_lưu_thuận_quỉ_niên_cốc_phong_đăng/HUAY_11_04_24_1056", "active": "1", "descendant": "", "entity": "3n2f05yc", "template": "", "type": "web_article", "relative": "0" },
  { "route": "Tiền_đồng_lớn/Tự_Đức_thông_bảo/Quốc_thái_dân_an_phong_điều_vũ_thuận/JNQ2_7", "active": "1", "descendant": "x", "entity": "srein1y0", "template": "", "type": "web_article", "relative": "0" },
  { "route": "Tiền_đồng_lớn/Tự_Đức_thông_bảo/Trung_hoà_vị_dục/CHCOIN_190317", "active": "1", "descendant": "", "entity": "jtrnzawl", "template": "", "type": "web_article", "relative": "0" }
]