[
  { "route": "", "active": "1", "descendant": "", "entity": "ws7wjcti", "template": "", "type": "auction", "relative": "1" },
  { "route": "Tiền_đồng_lớn/Minh_Mệnh_thông_bảo/Chí_công_chí_chính_vô_đảng_vô_thiên/HAE_2023_7712", "active": "1", "descendant": "", "entity": "ss8nt0ws", "template": "", "type": "auction", "relative": "0" },
  { "route": "Tiền_đồng_lớn/Minh_Mệnh_thông_bảo/Quốc_phú_binh_cường_nội_an_ngoại_tĩnh/HAE_2023_7714", "active": "1", "descendant": "", "entity": "ogc12sau", "template": "", "type": "auction", "relative": "0" },
  { "route": "Tiền_đồng_lớn/Minh_Mệnh_thông_bảo/Quốc_phú_binh_cường_nội_an_ngoại_tĩnh/HAE_2023_7715", "active": "1", "descendant": "", "entity": "2wxekgnk", "template": "", "type": "auction", "relative": "0" },
  { "route": "Tiền_đồng_lớn/Minh_Mệnh_thông_bảo/Vương_đạo_đãng_đãng_thánh_mô_dương_dương/HAE_2023_7713", "active": "1", "descendant": "", "entity": "pupsxi3i", "template": "", "type": "auction", "relative": "0" },
  { "route": "Tiền_đồng_lớn/Minh_Mệnh_thông_bảo/Cương_kiện_trung_chính/HAE_2023_7710", "active": "1", "descendant": "", "entity": "g5jvemuy", "template": "", "type": "auction", "relative": "0" },
  { "route": "Tiền_đồng_lớn/Minh_Mệnh_thông_bảo/Gia_cấp_nhân_túc/HAE_2023_7711", "active": "1", "descendant": "", "entity": "q9j7bzji", "template": "", "type": "auction", "relative": "0" },
  { "route": "Tiền_đồng_lớn/Thiệu_Trị_thông_bảo/Đắc_vị_đắc_lộc_đắc_danh_đắc_thọ/HAE_2018_7723", "active": "1", "descendant": "", "entity": "4czegswh", "template": "", "type": "auction", "relative": "0" },
  { "route": "Tiền_đồng_lớn/Thiệu_Trị_thông_bảo/Thân_thân_trưởng_trưởng_lão_lão_ấu_ấu/HAE_2023_7724", "active": "1", "descendant": "", "entity": "3fc3g3cl", "template": "", "type": "auction", "relative": "0" },
  { "route": "Tiền_đồng_lớn/Thiệu_Trị_thông_bảo/Thiên_hạ_đại_đồng/HAE_2023_7722", "active": "1", "descendant": "", "entity": "b0rcrwt3", "template": "", "type": "auction", "relative": "0" },
  { "route": "Tiền_đồng_lớn/Thiệu_Trị_thông_bảo/Giải_ôn_phụ_tài/HAE_2023_7723", "active": "1", "descendant": "", "entity": "id9tj7ev", "template": "", "type": "auction", "relative": "0" },
  { "route": "Tiền_đồng_lớn/Tự_Đức_thông_bảo/Thụ_lộc_vu_thiên_bảo_hựu_mạng_chi/HAE_2023_7734", "active": "1", "descendant": "", "entity": "r21ibyhq", "template": "", "type": "auction", "relative": "0" },
  { "route": "Tiền_đồng_lớn/Tự_Đức_thông_bảo/Thứ_chính_duy_hòa/HAE_2023_7733", "active": "1", "descendant": "", "entity": "sky3uutw", "template": "", "type": "auction", "relative": "0" }
]