[
  { "route": "", "active": "1", "descendant": "", "entity": "kkl9x92f", "template": "", "relative": "1" },
  { "route": "Tiền_kẽm_lớn/Minh_Mệnh_thông_bảo/Phúc_lỷ_tuy_tướng/Mitsuru_116", "active": "1", "descendant": "", "entity": "xth3buu7", "template": "", "relative": "0" },
  { "route": "Tiền_kẽm_lớn/Thiệu_Trị_thông_bảo/Phúc_lỷ_tuy_tướng/CHCOIN_4033460", "active": "1", "descendant": "", "entity": "r3khpuhn", "template": "", "relative": "0" },
  { "route": "Tiền_kẽm_lớn/Tự_Đức_thông_bảo/Phúc_lỷ_tuy_tướng/Mitsuru_274", "active": "1", "descendant": "", "entity": "tg38kijl", "template": "", "relative": "0" }
]