[
  { "route": "", "active": "1", "descendant": "", "entity": "mqsngosb", "template": "", "type": "specimen", "relative": "1" },
  { "route": "Lacroix_478", "active": "1", "descendant": "lacroix_478", "entity": "pcs2rhf3", "template": "", "type": "specimen", "relative": "1" },
  { "route": "Gzll_4", "active": "1", "descendant": "gzll_4", "entity": "4qk9q9wu", "template": "", "type": "specimen", "relative": "1" },
  { "route": "Gd_6", "active": "1", "descendant": "gd_6", "entity": "bdoq3405", "template": "", "type": "specimen", "relative": "1" },
  { "route": "BTTPHCM_63", "active": "1", "descendant": "bttphcm_63", "entity": "0v8bcg8f", "template": "", "type": "specimen", "relative": "1" },
  { "route": "ICOIN_201308_2", "active": "1", "descendant": "icoin_201308_2", "entity": "oxqrbumy", "template": "", "type": "specimen", "relative": "1" }
]